{"story":{"group_1":[{"bg":"bg_adv_21243.jpg","bgEffect":"shakeSmall","bgm":"bgm01_battle04","chara":[{"cheek":1,"face":"mtn_ex_020.exp.json","id":300800,"motion":200,"mouthOpen":1,"pos":2}],"flashEffect":"flashWhite2","nameRight":"志伸晶","textBg":"shout","textRight":"哈！[se:4061_landing_jump5]","turnChangeIn":"fadeIn","turnChangeOut":"fadeOut"},{"bgEffect":"shakeSmall","chara":[{"cheek":1,"face":"mtn_ex_020.exp.json","id":301200,"motion":200,"mouthOpen":1,"pos":0}],"flashEffect":"flashWhite2","nameLeft":"纯美雨","textBg":"shout","textLeft":"哼！[se:4061_landing_jump5]"},{"chara":[{"cheek":1,"face":"mtn_ex_050.exp.json","id":300800,"motion":0,"mouthOpen":1}],"textRight":"哈～"},{"chara":[{"cheek":1,"face":"mtn_ex_030.exp.json","id":300800,"motion":300}],"textRight":"你、你好强啊～@这就是中国拳法啊……"},{"chara":[{"cheek":1,"face":"mtn_ex_020.exp.json","id":301200,"motion":100}],"textLeft":"是我师父传授给我的苍碧拳@和魔法的融合技……"},{"chara":[{"cheek":1,"face":"mtn_ex_020.exp.json","id":301200}],"textLeft":"是我的功夫结晶……"},{"chara":[{"cheek":1,"face":"mtn_ex_001.exp.json","id":301200,"motion":0}],"textLeft":"你……@那是……空手道吗？"},{"chara":[{"cheek":0,"face":"mtn_ex_010.exp.json","id":300800,"motion":100}],"textRight":"正是！"},{"chara":[{"cheek":0,"face":"mtn_ex_050.exp.json","id":300800,"motion":0}],"textRight":"……那么，既然彼此都@看穿了对方的路数……"},{"chara":[{"cheek":0,"face":"mtn_ex_020.exp.json","id":301200}],"textLeft":"就用下一招决胜负吧！"},{"chara":[{"cheek":0,"face":"mtn_ex_020.exp.json","id":300800,"motion":100,"mouthOpen":1}],"flashEffect":"flashWhiteSlow1","textRight":"哈！"},{"chara":[{"cheek":0,"face":"mtn_ex_020.exp.json","id":301200,"motion":200,"mouthOpen":1}],"flashEffect":"flashWhiteSlow1","textLeft":"哼！"},{"bg":"black","bgm":"stop","textCenter":"到此为止！","turnChangeIn":"fadeIn","turnChangeOut":"fadeOut"},{"bg":"bg_adv_21243.jpg","chara":[{"cheek":0,"face":"mtn_ex_001.exp.json","id":301200,"motion":0,"pos":0}],"nameLeft":"纯美雨","surround":"7009_night_townbuzz","textLeft":"？@[chara:301200:cheek_0:face_mtn_ex_020.exp.json]是谁！？","turnChangeIn":"whiteIn","turnChangeOut":"whiteOut"},{"chara":[{"cheek":0,"face":"mtn_ex_030.exp.json","id":300800,"motion":300,"pos":2}],"nameRight":"志伸晶","textRight":"啊～累死了……@你喊停喊得太迟了吧？"},{"chara":[{"cheek":0,"face":"mtn_ex_010.exp.json","id":300500,"motion":0,"pos":2}],"nameRight":"？？？","textRight":"不好意思……@一不小心看入迷了！"},{"chara":[{"cheek":0,"face":"mtn_ex_020.exp.json","id":301200}],"textLeft":"你是？"},{"bgm":"bgm03_story06","chara":[{"id":300500,"motion":100}],"nameRight":"常盘七香","surround":"stop","textRight":"对不起，现在才和你打招呼……@我是[textRed:常盘七香]。"},{"chara":[{"id":300500}],"textRight":"我也是魔法少女。@[chara:300500:lipSynch_0][wait:1.0][chara:300500:lipSynch_1][chara:300500:cheek_-1:face_mtn_ex_030.exp.json:motion_000]今后让我们友好相处吧……"},{"narration":"这位名叫[textRed:七香]的少女@向美雨说明了情况……","narrationBg":"bg_adv_21243.jpg","narrationEffect":"in"},{"chara":[{"cheek":0,"face":"mtn_ex_050.exp.json","id":301200}],"nameLeft":"纯美雨","narrationEffect":"out","textLeft":"什么……"},{"chara":[{"cheek":0,"face":"mtn_ex_020.exp.json","id":301200,"motion":400}],"textLeft":"这次的收购土地骚动@也与魔女有关吗！？"},{"chara":[{"cheek":-1,"face":"mtn_ex_020.exp.json","id":300500}],"nameRight":"常盘七香","textRight":"是的……@我们在找那个魔女。"},{"chara":[{"id":300500,"motion":300}],"textRight":"魔女操纵着人们的恶意，@在世间散布灾厄……"},{"chara":[{"id":300500}],"textRight":"这次也不例外@……只是情况有些特殊。"},{"chara":[{"cheek":-1,"face":"mtn_ex_050.exp.json","id":300500,"motion":0}],"textRight":"所以我们才伪装成@土地开发商的中间人。"},{"chara":[{"cheek":0,"face":"mtn_ex_001.exp.json","id":301200,"motion":0}],"textLeft":"这是……@你安排的？"},{"chara":[{"cheek":-1,"face":"mtn_ex_030.exp.json","id":300500}],"textRight":"是的。@我在各方面做了准备……"},{"chara":[{"id":300500}],"textRight":"然后将佳子作为保镖@送了过来。"},{"chara":[{"id":300500,"motion":100}],"textRight":"我和晶负责支援佳子，@同时收集周围的消息……"},{"chara":[{"cheek":0,"face":"mtn_ex_020.exp.json","id":301200,"lipSynch":0}],"textLeft":"（这家伙……是什么人？）"},{"chara":[{"cheek":-1,"face":"mtn_ex_010.exp.json","id":300500,"motion":0}],"textRight":"在此过程中，@我们也听说了你的消息……"},{"chara":[{"cheek":0,"face":"mtn_ex_001.exp.json","id":301200,"motion":200}],"textLeft":"听说了@我是魔法少女？"},{"chara":[{"id":300500}],"textRight":"是的，@我们是从其他魔法少女那里听来的。"},{"chara":[{"cheek":-1,"face":"mtn_ex_030.exp.json","id":300500,"motion":100}],"textRight":"所以……很抱歉，@我们决定试探你。"},{"chara":[{"cheek":-1,"face":"mtn_ex_010.exp.json","id":300500}],"textRight":"试探你的实力。"},{"chara":[{"cheek":1,"face":"mtn_ex_030.exp.json","id":301100,"motion":300,"pos":2}],"nameRight":"夏目佳子","textRight":"我完全不是对手！"},{"chara":[{"cheek":0,"face":"mtn_ex_050.exp.json","id":300800,"motion":0,"pos":2}],"nameRight":"志伸晶","textRight":"我也竭尽全力了。@[chara:300800:lipSynch_0][wait:1.0][chara:300800:lipSynch_1][chara:300800:cheek_0:face_mtn_ex_010.exp.json]你真强啊！"},{"chara":[{"cheek":0,"face":"mtn_ex_030.exp.json","id":301200,"motion":0}],"textLeft":"你们的目的是什么？"},{"chara":[{"cheek":-1,"face":"mtn_ex_050.exp.json","id":300500,"motion":0,"pos":2}],"nameRight":"常盘七香","textRight":"那我就直说了。"},{"chara":[{"id":300500}],"textRight":"你要不要和我们一起……@追踪和这次事件有关的魔女？"},{"chara":[{"cheek":0,"face":"mtn_ex_020.exp.json","id":301200,"lipSynch":0}],"textLeft":"……@[chara:301200:lipSynch_0][wait:1.0][chara:301200:lipSynch_1][chara:301200:lipSynch_1]联手……吗……"},{"chara":[{"cheek":-1,"face":"mtn_ex_030.exp.json","id":300500,"motion":300}],"textRight":"没错……"},{"chara":[{"cheek":-1,"face":"mtn_ex_020.exp.json","id":300500,"motion":0}],"textRight":"这次情况非常特殊……我希望能和@其他魔法少女联手对应。"},{"chara":[{"id":300500}],"textRight":"你意下如何？"},{"chara":[{"cheek":0,"face":"mtn_ex_030.exp.json","id":301200,"lipSynch":0,"motion":300}],"textLeft":"…………"},{"chara":[{"cheek":0,"face":"mtn_ex_001.exp.json","id":301200,"motion":0}],"textLeft":"让我@考虑一下吧……"},{"chara":[{"cheek":0,"face":"mtn_ex_030.exp.json","id":301100,"motion":100,"pos":2}],"nameRight":"夏目佳子","textRight":"也就是说……@你先保留意见啊……"},{"chara":[{"cheek":0,"face":"mtn_ex_020.exp.json","id":301200}],"textLeft":"现在我还有@其他事情需要优先处理。"},{"chara":[{"cheek":0,"face":"mtn_ex_010.exp.json","id":300500,"motion":100,"pos":2}],"nameRight":"常盘七香","textRight":"呵呵……@确实如此。"},{"chara":[{"cheek":0,"face":"mtn_ex_001.exp.json","id":301200,"motion":200}],"textLeft":"我去告诉大家@问题解决了。"},{"chara":[{"cheek":0,"face":"mtn_ex_001.exp.json","id":301200,"motion":0}],"textLeft":"街上的居民@都在等这个消息。"},{"chara":[{"cheek":0,"face":"mtn_ex_001.exp.json","id":301200,"motion":400,"pos":1},{"effect":"fadeout","id":300500}],"nameCenter":"纯美雨","nameLeft":"","textCenter":"这是我的职责……@不……"},{"chara":[{"cheek":0,"face":"mtn_ex_020.exp.json","id":301200,"motion":200}],"textCenter":"是苍海帮的职责！"},{"autoTurnFirst":1.8,"bg":"bg_adv_narration.jpg","bgm":"stop","chara":[{"cheek":-1,"face":"mtn_ex_050.exp.json","id":301200,"motion":0,"pos":1,"voice":"vo_char_3012_00_05","textHome":"呼——事件姑且是告一段落了……姑且啊……"}],"nameCenter":"纯美雨","textCenter":"嗯……这件事姑且算是@告一段落了吧……姑且……","turnChangeIn":"fadeIn","turnChangeOut":"fadeOut","turnEffect":"stop"},{"autoTurnFirst":4.0,"chara":[{"cheek":1,"face":"mtn_ex_010.exp.json","id":301200,"motion":100}]},{"autoTurnFirst":3.0,"chara":[{"cheek":-1,"face":"mtn_ex_020.exp.json","id":301200,"motion":200}]},{"chara":[{"id":301200}]},{"autoTurnLast":2.0,"turnChangeIn":"fadeIn"}]},"version":3}